devint/__init__.py
devint/base/__init__.py
devint/base/device.py
devint/base/interface.py
devint/base/protocol.py
devint/base/register.py
devint/base/service.py
devint/device_manager.py
devint/interfaces/__init__.py
devint/interfaces/can.py
devint/interfaces/gpio.py
devint/interfaces/i2c.py
devint/interfaces/i2s.py
devint/interfaces/one_wire.py
devint/interfaces/serial.py
devint/interfaces/spi.py
devint/interfaces/tcp.py
devint/interfaces/udp.py
devint/protocols/__init__.py
devint/protocols/canopen.py
devint/protocols/gpio_protocol.py
devint/protocols/i2c_smbus.py
devint/protocols/modbus_rtu.py
devint/protocols/modbus_tcp.py
devint/protocols/mqtt.py
devint/protocols/spi_protocol.py
devint/registry/__init__.py
devint/registry/generic/__init__.py
devint/registry/raspberry_pi/__init__.py
devint/registry/raspberry_pi/explorer_hat.py
devint/registry/raspberry_pi/generic_hat.py
devint/registry/raspberry_pi/piface.py
devint/registry/raspberry_pi/sense_hat.py
devint/registry/waveshare/__init__.py
devint/registry/waveshare/io_8ch.py
devint/services/__init__.py
devint/services/device_service.py
devint/services/discovery.py
devint/services/multi_service.py
devint/tests/__init__.py
devint/tests/test_devices.py
devint/tests/test_integration.py
devint/tests/test_interfaces.py
devint/tests/test_services.py
devint-0.2.5.dist-info/LICENSE
devint-0.2.5.dist-info/METADATA
devint-0.2.5.dist-info/WHEEL
devint-0.2.5.dist-info/entry_points.txt
devint-0.2.5.dist-info/RECORD
