Metadata-Version: 2.3
Name: devint
Version: 0.2.5
Summary: Unified Device Interface - A Python library for interacting with various hardware devices and protocols
License: Apache-2.0
Author: Tom Sapletta
Author-email: info@softreck.dev
Requires-Python: >=3.10,<4.0
Classifier: Development Status :: 3 - Alpha
Classifier: Intended Audience :: Developers
Classifier: Intended Audience :: Manufacturing
Classifier: Intended Audience :: Science/Research
Classifier: License :: OSI Approved :: Apache Software License
Classifier: Operating System :: OS Independent
Classifier: Programming Language :: Python :: 3
Classifier: Programming Language :: Python :: 3.10
Classifier: Programming Language :: Python :: 3.11
Classifier: Programming Language :: Python :: 3.12
Classifier: Programming Language :: Python :: 3.13
Classifier: Topic :: Home Automation
Classifier: Topic :: Scientific/Engineering
Classifier: Topic :: Software Development :: Embedded Systems
Classifier: Topic :: System :: Hardware
Classifier: Topic :: System :: Hardware :: Hardware Drivers
Classifier: Typing :: Typed
Requires-Dist: flask (>=2.3.3,<3.0.0)
Requires-Dist: paho-mqtt (>=2.0.0,<3.0.0)
Requires-Dist: pyserial (>=3.5,<4.0)
Requires-Dist: python-dotenv (>=1.0.0,<2.0.0)
Requires-Dist: requests (>=2.31.0,<3.0.0)
Project-URL: Bug Tracker, https://github.com/pyfunc/devint/issues
Project-URL: Documentation, https://github.com/pyfunc/devint#readme
Project-URL: Homepage, https://github.com/pyfunc/devint
